startme/mods/ex_boot/__init__.py
startme/mods/ex_cron/__init__.py
startme_examples-0.1.dist-info/LICENSE
startme_examples-0.1.dist-info/METADATA
startme_examples-0.1.dist-info/WHEEL
startme_examples-0.1.dist-info/top_level.txt
startme_examples-0.1.dist-info/RECORD
